pytopo/GenericMapCollection.py
pytopo/MapCollection.py
pytopo/MapUtils.py
pytopo/MapViewer.py
pytopo/MapWindow.py
pytopo/OSMMapCollection.py
pytopo/TiledMapCollection.py
pytopo/TopoMapCollection.py
pytopo/TrackPoints.py
pytopo/__init__.py
pytopo/configfile.py
pytopo/gpsdPoller.py
pytopo/trackstats.py
pytopo/resources/pytopo-pin.png
pytopo/resources/pytopo.desktop
pytopo/resources/pytopo.png
pytopo/resources/sample.pytopo
pytopo-1.7.3.dist-info/COPYING
pytopo-1.7.3.dist-info/METADATA
pytopo-1.7.3.dist-info/WHEEL
pytopo-1.7.3.dist-info/entry_points.txt
pytopo-1.7.3.dist-info/top_level.txt
pytopo-1.7.3.dist-info/RECORD
