Metadata-Version: 2.1
Name: pytopo
Version: 1.7.3
Summary: Tiled map viewer and track editor
Home-page: http://shallowsky.com/software/topo/
Author: Akkana Peck
Author-email: akkana@shallowsky.com
License: GPLv2+
Project-URL: Source Code, https://github.com/akkana/pytopo/
Project-URL: Documentation, https://pytopo.readthedocs.io/
Project-URL: Bug Tracker, https://github.com/akkana/pytopo/issues
Keywords: maps,map viewer,track files,track logs,GPX,KML,GeoJSON
Classifier: Programming Language :: Python :: 3
Classifier: License :: OSI Approved :: GNU General Public License v2 or later (GPLv2+)
Classifier: Intended Audience :: End Users/Desktop
Classifier: Intended Audience :: Science/Research
Classifier: Topic :: Scientific/Engineering :: GIS
License-File: COPYING
Requires-Dist: PyGObject
Requires-Dist: pycairo
Requires-Dist: requests-futures
Requires-Dist: simplejson
Provides-Extra: elliplots
Requires-Dist: matplotlib; extra == "elliplots"
Requires-Dist: numpy; extra == "elliplots"
